pywrb/__init__.py
pywrb/constants.py
pywrb/entrypoint.py
pywrb/io.py
pywrb/xarray.py
pywrb-0.1.3.dist-info/licenses/LICENSE.md
pywrb-0.1.3.dist-info/METADATA
pywrb-0.1.3.dist-info/WHEEL
pywrb-0.1.3.dist-info/entry_points.txt
pywrb-0.1.3.dist-info/top_level.txt
pywrb-0.1.3.dist-info/RECORD
