Metadata-Version: 2.4
Name: pywrb
Version: 0.1.3
Summary: Wind Resource binary reader and writer
Author-email: Thijs van Winden <thijs.vanwinden@whiffle.nl>
License-Expression: MIT
License-File: LICENSE.md
Requires-Dist: numpy
Provides-Extra: xarray
Requires-Dist: xarray; extra == "xarray"
Requires-Dist: rioxarray; extra == "xarray"
Provides-Extra: dev
Requires-Dist: pytest; extra == "dev"
Requires-Dist: xarray; extra == "dev"
Requires-Dist: rioxarray; extra == "dev"
Dynamic: license-file
